<BackupInst xmlns="http://www.microsoft.com/GroupPolicy/GPOOperations/Manifest"><GPOGuid><![CDATA[{CF17F28D-D627-42A1-B7A9-574C002FD97F}]]></GPOGuid><GPODomain><![CDATA[idl.local]]></GPODomain><GPODomainGuid><![CDATA[{21ae17e9-5746-4c0a-ab06-86222e0eb1d7}]]></GPODomainGuid><GPODomainController><![CDATA[DC-IDL-01.idl.local]]></GPODomainController><BackupTime><![CDATA[2016-12-09T14:42:24]]></BackupTime><ID><![CDATA[{B30BE6B3-794A-43CC-B6A4-52C447CEE0A7}]]></ID><Comment><![CDATA[]]></Comment><GPODisplayName><![CDATA[DoD Windows 10 STIG - User (SHB v10.1.0)]]></GPODisplayName></BackupInst>
